chado/__init__.py
chado/client.py
chado/exceptions.py
chado/util.py
chado/analysis/__init__.py
chado/export/__init__.py
chado/expression/__init__.py
chado/feature/__init__.py
chado/load/__init__.py
chado/organism/__init__.py
chado/phylogeny/__init__.py
chado/util/__init__.py
chakin/__init__.py
chakin/cli.py
chakin/config.py
chakin/decorators.py
chakin/io.py
chakin/commands/__init__.py
chakin/commands/cmd_analysis.py
chakin/commands/cmd_export.py
chakin/commands/cmd_expression.py
chakin/commands/cmd_feature.py
chakin/commands/cmd_init.py
chakin/commands/cmd_load.py
chakin/commands/cmd_organism.py
chakin/commands/cmd_phylogeny.py
chakin/commands/cmd_util.py
chakin/commands/analysis/__init__.py
chakin/commands/analysis/add_analysis.py
chakin/commands/analysis/delete_analyses.py
chakin/commands/analysis/get_analyses.py
chakin/commands/export/__init__.py
chakin/commands/export/export_fasta.py
chakin/commands/export/export_gbk.py
chakin/commands/export/export_gff3.py
chakin/commands/expression/__init__.py
chakin/commands/expression/add_biomaterial.py
chakin/commands/expression/add_expression.py
chakin/commands/expression/delete_all_biomaterials.py
chakin/commands/expression/delete_biomaterial.py
chakin/commands/expression/delete_biomaterials.py
chakin/commands/expression/get_biomaterials.py
chakin/commands/feature/__init__.py
chakin/commands/feature/delete_features.py
chakin/commands/feature/get_feature_analyses.py
chakin/commands/feature/get_feature_cvterms.py
chakin/commands/feature/get_features.py
chakin/commands/feature/load_fasta.py
chakin/commands/feature/load_featureprops.py
chakin/commands/feature/load_gff.py
chakin/commands/feature/load_go.py
chakin/commands/load/__init__.py
chakin/commands/load/blast.py
chakin/commands/load/go.py
chakin/commands/load/interpro.py
chakin/commands/organism/__init__.py
chakin/commands/organism/add_organism.py
chakin/commands/organism/delete_all_organisms.py
chakin/commands/organism/delete_organisms.py
chado-2.3.9.dist-info/LICENSE.txt
chado-2.3.9.dist-info/METADATA
chado-2.3.9.dist-info/WHEEL
chado-2.3.9.dist-info/entry_points.txt
chado-2.3.9.dist-info/top_level.txt
chado-2.3.9.dist-info/RECORD
